{
	"configurations" : 
	[
		{
			"directories" : 
			[
				{
					"build" : ".",
					"hasInstallRule" : true,
					"jsonFile" : "directory-.-Debug-731e9228db69ab8b1139.json",
					"minimumCMakeVersion" : 
					{
						"string" : "3.12"
					},
					"projectIndex" : 0,
					"source" : ".",
					"targetIndexes" : 
					[
						0,
						1,
						2
					]
				}
			],
			"name" : "Debug",
			"projects" : 
			[
				{
					"directoryIndexes" : 
					[
						0
					],
					"name" : "plan_env",
					"targetIndexes" : 
					[
						0,
						1,
						2
					]
				}
			],
			"targets" : 
			[
				{
					"directoryIndex" : 0,
					"id" : "plan_env::@6890427a1f51a3e7e1df",
					"jsonFile" : "target-plan_env-Debug-f86708db1dd3c7913ad1.json",
					"name" : "plan_env",
					"projectIndex" : 0
				},
				{
					"directoryIndex" : 0,
					"id" : "plan_env_uninstall::@6890427a1f51a3e7e1df",
					"jsonFile" : "target-plan_env_uninstall-Debug-23064467dfed03b5b295.json",
					"name" : "plan_env_uninstall",
					"projectIndex" : 0
				},
				{
					"directoryIndex" : 0,
					"id" : "uninstall::@6890427a1f51a3e7e1df",
					"jsonFile" : "target-uninstall-Debug-ba93bfc68bded2459b82.json",
					"name" : "uninstall",
					"projectIndex" : 0
				}
			]
		}
	],
	"kind" : "codemodel",
	"paths" : 
	{
		"build" : "/home/hy/ACE/src/Kinodynamic_esdf_mpc/plan_env/build",
		"source" : "/home/hy/ACE/src/Kinodynamic_esdf_mpc/plan_env"
	},
	"version" : 
	{
		"major" : 2,
		"minor" : 5
	}
}
